{"en":{"0":{"i":229973,"c":3566},"1":{"i":1291332,"c":101115},"2":{"i":1071983,"c":399372},"3":{"i":522704,"c":685884},"4":{"c":739930,"i":172738},"5":{"c":1152978,"i":49215},"6":{"c":1188653,"i":10650},"7":{"c":40215,"i":1},"8":{"c":2238}},"de":{"0":{"i":168256,"c":26392},"1":{"i":234092,"c":119339},"2":{"i":223553,"c":457970},"3":{"i":71964,"c":690674},"4":{"c":219709,"i":5687},"5":{"c":85370,"i":3492},"6":{"c":86214,"i":3259},"7":{"c":24834,"i":295},"8":{"c":1396},"9":{"c":1}},"it":{"0":{"i":193608,"c":8871},"1":{"c":1830,"i":37783},"2":{"i":8075,"c":880},"3":{"i":2557,"c":6538},"4":{"i":219,"c":934},"5":{"i":124,"c":430},"6":{"c":368,"i":127},"7":{"c":199,"i":10},"8":{"c":136,"i":3},"9":{"c":20,"i":2},"10":{"c":3},"11":{"c":1},"12":{"c":1}},"es":{"0":{"i":1087,"c":32},"1":{"i":9673,"c":969},"2":{"i":12381,"c":2794},"3":{"i":64468,"c":11390},"4":{"i":105871,"c":114431},"5":{"c":196504,"i":56830},"6":{"c":174942,"i":22260},"7":{"c":126587,"i":5432},"8":{"c":48030,"i":871},"9":{"c":7156,"i":107},"10":{"c":598,"i":25},"11":{"c":78,"i":5},"12":{"c":11},"13":{"c":1,"i":1},"14":{"c":2}},"he":{"0":{"i":3569},"1":{"i":30704},"2":{"i":5013},"3":{"i":81}},"el":{"0":{"i":7,"c":2},"1":{"i":3},"3":{"i":1},"4":{"i":1},"5":{"c":1},"8":{"c":1}},"eu":{"0":{"i":361080},"1":{"i":223514},"2":{"i":46659},"3":{"i":52918},"4":{"i":37246},"5":{"i":36674},"6":{"i":4278},"7":{"i":13},"8":{"i":1},"9":{"i":2},"10":{"i":2},"11":{"i":1}},"nl":{"0":{"i":5786,"c":511},"1":{"i":2055,"c":196},"2":{"c":4204,"i":5201},"3":{"c":60160,"i":18492},"4":{"c":703664,"i":12634},"5":{"c":312186,"i":4691},"6":{"c":155234,"i":1366},"7":{"c":92669,"i":674},"8":{"c":27871,"i":538},"9":{"c":2949,"i":391},"10":{"i":217,"c":378},"11":{"i":81,"c":80},"12":{"i":9,"c":6},"13":{"c":1,"i":1},"14":{"i":1}},"fi":{"0":{"i":116045,"c":13331},"1":{"i":182944,"c":61057},"2":{"c":6709,"i":15206},"3":{"i":462,"c":88},"4":{"c":1,"i":8}},"sv":{"0":{"i":266521,"c":9},"1":{"i":63437,"c":76},"2":{"i":5487,"c":3750},"3":{"c":59066,"i":33980},"4":{"c":253312,"i":99741},"5":{"c":406321,"i":54269},"6":{"c":315690,"i":20987},"7":{"i":2853,"c":72165},"8":{"i":942,"c":18897},"9":{"i":136,"c":1799},"10":{"i":26,"c":72},"11":{"i":4,"c":4},"12":{"i":1},"13":{"i":1}},"fr":{"0":{"i":82588,"c":8649},"1":{"c":110765,"i":113832},"2":{"c":377221,"i":127770},"3":{"c":793197,"i":91512},"4":{"c":434403,"i":8370},"5":{"c":81747,"i":558},"6":{"c":101835,"i":837},"7":{"c":42687,"i":279},"8":{"c":3070}},"pl":{"0":{"i":6901,"c":2649},"1":{"i":16289,"c":20846},"2":{"i":11353,"c":16265},"3":{"c":118915,"i":21932},"4":{"c":418263,"i":9658},"5":{"c":607851,"i":2350},"6":{"c":178124,"i":917},"7":{"c":485,"i":299},"8":{"i":71,"c":53},"9":{"i":10,"c":15},"11":{"i":1},"12":{"i":1}},"tt":{"0":{"i":663},"1":{"i":625},"2":{"i":14}},"am":{"0":{"i":16561},"1":{"i":712},"2":{"i":45},"3":{"i":2}},"tg":{"0":{"i":17437},"1":{"i":4052},"2":{"i":1573},"3":{"i":4343},"4":{"i":2204},"5":{"i":1230},"6":{"i":840},"7":{"i":397},"8":{"i":140},"9":{"i":56},"10":{"i":17},"11":{"i":7},"15":{"i":1}},"fy":{"0":{"i":24253},"1":{"i":1595},"2":{"i":731}},"uk":{"0":{"i":60120,"c":36891},"1":{"c":91090,"i":60515},"2":{"i":4074,"c":16924},"3":{"i":85,"c":629},"4":{"i":1}},"ur":{"0":{"i":45693},"1":{"i":12396},"2":{"i":4945},"3":{"i":258}},"sr":{"0":{"i":6110},"1":{"i":13966},"2":{"i":2261},"3":{"i":17}},"ne":{"0":{"i":29851},"1":{"i":69292},"2":{"i":38993},"3":{"i":414},"4":{"i":99},"5":{"i":26},"6":{"i":4}},"lt":{"0":{"c":54952,"i":35297},"1":{"c":87826,"i":62872},"2":{"c":13497,"i":7238},"3":{"c":548,"i":91},"4":{"c":6}},"jv":{"0":{"i":68912},"1":{"i":82534},"2":{"i":2595},"3":{"i":2155},"4":{"i":1605},"5":{"i":4891},"6":{"i":2367},"7":{"i":20},"8":{"i":2},"9":{"i":1},"10":{"i":1},"11":{"i":1}},"lb":{"0":{"i":88151},"1":{"i":13040},"2":{"i":2398},"3":{"i":49}},"vo":{"0":{"i":192470},"1":{"i":180652},"2":{"i":41133},"3":{"i":36608},"4":{"i":23506},"5":{"i":48019},"6":{"i":354},"7":{"i":123},"8":{"i":26},"9":{"i":1},"10":{"i":1}},"ml":{"0":{"i":54913},"1":{"i":28462},"2":{"i":9232},"3":{"i":4462},"4":{"i":4840},"5":{"i":9365},"6":{"i":2232},"7":{"i":588},"8":{"i":60},"9":{"i":6},"10":{"i":1}},"is":{"0":{"i":19749,"c":5555},"1":{"i":13120,"c":7563},"2":{"i":1236,"c":1491},"3":{"c":98,"i":40},"4":{"c":2}},"sl":{"0":{"i":184977}},"sq":{"0":{"i":31019},"1":{"i":37883},"2":{"i":10890},"3":{"i":1124},"4":{"i":147},"5":{"i":33},"6":{"i":8}},"la":{"0":{"i":13},"1":{"i":592},"2":{"i":3369},"3":{"i":18468},"4":{"i":18386},"5":{"i":13475},"6":{"i":14045},"7":{"i":1744},"8":{"i":301},"9":{"i":56},"10":{"i":7},"11":{"i":2}},"te":{"0":{"i":3198},"1":{"i":5192},"2":{"i":1548},"3":{"i":959},"4":{"i":1482},"5":{"i":5847},"6":{"i":812},"7":{"i":5},"8":{"i":2}},"bn":{"0":{"i":23539},"1":{"i":5470},"2":{"i":7308},"3":{"i":8933},"4":{"i":5530},"5":{"i":7454},"6":{"i":6389},"7":{"i":3389},"8":{"i":1053},"9":{"i":97},"10":{"i":13},"11":{"i":3}},"ta":{"0":{"i":59056},"1":{"i":59204},"2":{"i":12556},"3":{"i":1958},"4":{"i":474},"5":{"i":108},"6":{"i":25},"7":{"i":1}},"th":{"0":{"i":16405,"c":18946},"1":{"c":14627,"i":8197},"2":{"c":536,"i":408},"3":{"i":13,"c":1},"4":{"i":1}},"cs":{"0":{"i":283706},"1":{"i":277897},"2":{"i":53958},"3":{"i":33760},"4":{"i":82099},"5":{"i":145899},"6":{"i":85919},"7":{"i":303},"8":{"i":97},"9":{"i":15},"10":{"i":2},"11":{"i":3}},"vi":{"0":{"i":7963},"1":{"i":23251},"2":{"i":26227},"3":{"i":53754},"4":{"i":225829},"5":{"i":82509},"6":{"i":38954},"7":{"i":19213},"8":{"i":8308},"9":{"i":1657},"10":{"i":468},"11":{"i":40},"12":{"i":6},"14":{"i":1}},"af":{"0":{"i":52448},"1":{"i":18152},"2":{"i":3993},"3":{"i":1365},"4":{"i":2015},"5":{"i":3771},"6":{"i":4288},"7":{"i":3},"8":{"i":2}},"et":{"0":{"i":56142,"c":15455},"1":{"c":17911,"i":30498},"2":{"c":7343,"i":6350},"3":{"c":8935,"i":948},"4":{"c":12300,"i":309},"5":{"c":15248,"i":148},"6":{"c":9563,"i":41},"7":{"c":5297,"i":29},"8":{"c":1714,"i":21},"9":{"c":280,"i":12},"10":{"c":38,"i":3},"11":{"c":9,"i":6},"12":{"c":1,"i":1},"13":{"c":1}},"gd":{"0":{"i":1284},"1":{"i":764},"2":{"i":333},"3":{"i":832},"4":{"i":1729},"5":{"i":1845},"6":{"i":1415},"7":{"i":529},"8":{"i":132},"9":{"i":23},"10":{"i":3}},"ka":{"0":{"i":28092},"1":{"i":48228},"2":{"i":8007},"3":{"i":3059},"4":{"i":7527},"5":{"i":10687},"6":{"i":8070},"7":{"i":3004},"8":{"i":621},"9":{"i":73},"10":{"i":12},"11":{"i":5},"12":{"i":2}},"io":{"0":{"i":8648},"1":{"i":13644},"2":{"i":5873},"3":{"i":1441},"4":{"i":19}},"ko":{"0":{"i":290030},"1":{"i":312031},"2":{"i":93496},"3":{"i":30373},"4":{"i":35086},"5":{"i":32239},"6":{"i":28253},"7":{"i":43},"8":{"i":4}},"sw":{"0":{"i":1},"1":{"i":192},"2":{"i":3815},"3":{"i":1783},"4":{"i":4083},"5":{"i":4747},"6":{"i":2610},"7":{"i":1202},"8":{"i":279},"9":{"i":27},"10":{"i":1}},"da":{"0":{"c":144,"i":4667},"1":{"c":579,"i":14426},"2":{"i":3661,"c":419},"3":{"i":3853,"c":1526},"4":{"i":10713,"c":4942},"5":{"c":17006,"i":26150},"6":{"c":16413,"i":22089},"7":{"i":13,"c":2},"8":{"i":5}},"lv":{"0":{"i":230554},"1":{"i":182820},"2":{"i":46977},"3":{"i":8338},"4":{"i":7259},"5":{"i":16890},"6":{"i":5980},"7":{"i":50},"8":{"i":12}},"mg":{"0":{"i":73},"1":{"i":21},"2":{"i":711},"3":{"i":7397},"4":{"i":21507},"5":{"i":2632},"6":{"i":5030},"7":{"i":345},"8":{"i":46},"9":{"i":9},"10":{"i":3}},"ro":{"0":{"i":604599,"c":38490},"1":{"i":286828,"c":71237},"2":{"i":75400,"c":64145},"3":{"c":17470,"i":12340},"4":{"c":2529,"i":1456},"5":{"i":450,"c":734},"6":{"c":353,"i":144},"7":{"c":87,"i":26},"8":{"c":17,"i":11},"9":{"i":4,"c":2},"10":{"i":1}},"gl":{"0":{"c":3841,"i":117042},"1":{"i":59815,"c":11998},"2":{"i":16089,"c":10432},"3":{"i":3426,"c":6038},"4":{"c":15568,"i":752},"5":{"c":31026,"i":1160},"6":{"c":18550,"i":77},"7":{"c":8423,"i":170},"8":{"c":2305,"i":12},"9":{"c":280,"i":1},"10":{"c":23,"i":1},"11":{"c":7,"i":1},"12":{"c":6,"i":1},"14":{"c":1}},"id":{"0":{"i":22112},"1":{"i":58220},"2":{"i":21997},"3":{"i":13843},"4":{"i":102},"5":{"i":23},"6":{"i":8},"7":{"i":4}},"ca":{"0":{"i":875706,"c":23829},"1":{"i":1047764,"c":136939},"2":{"i":256220,"c":218107},"3":{"c":63136,"i":38533},"4":{"i":5112,"c":7224},"5":{"c":3105,"i":999},"6":{"c":1367,"i":240},"7":{"c":258,"i":42},"8":{"c":75,"i":5},"9":{"c":13},"10":{"c":8,"i":2}},"tl":{"0":{"i":637620},"1":{"i":432630},"2":{"i":3419},"3":{"i":94}},"bs":{"0":{"i":37372},"1":{"i":27810},"2":{"i":8521},"3":{"i":6478},"4":{"i":11245},"5":{"i":21822},"6":{"i":12417},"7":{"i":6806},"8":{"i":2090},"9":{"i":312},"10":{"i":62},"11":{"i":23},"12":{"i":2},"13":{"i":1}},"zh":{"0":{"i":31654},"1":{"i":32402},"2":{"i":6177},"3":{"i":1877},"4":{"i":627},"5":{"i":197},"6":{"i":40},"7":{"i":5},"8":{"i":4},"9":{"i":1}},"mk":{"0":{"i":4227},"1":{"i":22213},"2":{"i":11294},"3":{"i":208},"4":{"i":1}},"ru":{"0":{"i":102789,"c":28904},"1":{"i":165941,"c":96999},"2":{"c":30008,"i":22593},"3":{"i":1559,"c":2465},"4":{"c":16,"i":4}},"tr":{"0":{"i":8679},"1":{"i":60043},"2":{"i":19163},"3":{"i":121}},"wa":{"0":{"i":3705},"1":{"i":36},"2":{"i":121},"3":{"i":785},"4":{"i":2735},"5":{"i":4544},"6":{"i":4682},"7":{"i":1640},"8":{"i":540},"9":{"i":120},"10":{"i":16},"11":{"i":2},"12":{"i":1}},"gu":{"0":{"i":3024},"1":{"i":3715},"2":{"i":230},"3":{"i":3}},"mr":{"0":{"i":13560},"1":{"i":43244},"2":{"i":9185},"3":{"i":9455},"4":{"i":9404},"5":{"i":7898},"6":{"i":3630},"7":{"i":944},"8":{"i":281},"9":{"i":95},"10":{"i":25},"11":{"i":9},"12":{"i":3},"13":{"i":1},"15":{"i":1}},"fa":{"0":{"i":23626,"c":9420},"1":{"c":8150,"i":2289},"2":{"c":2639,"i":1884},"3":{"c":17908,"i":218},"4":{"c":41340,"i":102},"5":{"c":29699,"i":133},"6":{"c":28902,"i":119},"7":{"c":44,"i":35},"8":{"c":10,"i":2},"9":{"c":1,"i":1},"10":{"i":1}},"hu":{"0":{"i":134059,"c":37469},"1":{"i":219449,"c":70770},"2":{"c":32476,"i":33029},"3":{"c":17772,"i":2230},"4":{"i":594,"c":29280},"5":{"c":19535,"i":209},"6":{"c":16835,"i":264},"7":{"c":9608,"i":95},"8":{"c":2661,"i":67},"9":{"c":345,"i":21},"10":{"c":56,"i":16},"11":{"c":9,"i":3},"12":{"c":1,"i":1}},"ku":{"0":{"i":1303},"1":{"i":2169},"2":{"i":653},"3":{"i":1003},"4":{"i":2007},"5":{"i":3264},"6":{"i":784},"7":{"i":329},"8":{"i":99},"9":{"i":30},"10":{"i":11},"11":{"i":2},"12":{"i":1}},"ba":{"0":{"i":3472},"1":{"i":3270},"2":{"i":847},"3":{"i":177},"4":{"i":29},"5":{"i":5}},"be":{"0":{"i":87993,"c":56643},"1":{"c":63292,"i":34686},"2":{"c":21412,"i":6966},"3":{"c":6663,"i":854},"4":{"c":8379,"i":87},"5":{"i":21,"c":14429},"6":{"c":3530,"i":14},"7":{"c":8,"i":1},"8":{"c":3,"i":1},"9":{"c":1}},"hr":{"0":{"i":343757},"1":{"i":81080},"2":{"i":22005},"3":{"i":13789},"4":{"i":15750},"5":{"i":18681},"6":{"i":17852},"7":{"i":10162},"8":{"i":2952},"9":{"i":313},"10":{"i":36},"11":{"i":2}},"hi":{"0":{"i":136486},"1":{"i":52484},"2":{"i":22826},"3":{"i":25694},"4":{"i":30258},"5":{"i":16532},"6":{"i":25911},"7":{"i":5966},"8":{"i":2100},"9":{"i":481},"10":{"i":115},"11":{"i":24},"12":{"i":19},"13":{"i":5}},"kk":{"1":{"i":112}},"bg":{"0":{"i":406305},"1":{"i":424671},"2":{"i":129265},"3":{"i":34843},"4":{"i":46012},"5":{"i":56868},"6":{"i":52534},"7":{"i":32561},"8":{"i":10596},"9":{"i":1598},"10":{"i":257},"11":{"i":47},"12":{"i":4}},"yo":{"0":{"i":17251},"1":{"i":17592},"2":{"i":6394},"3":{"i":1542},"4":{"i":577},"5":{"i":105},"6":{"i":18},"7":{"i":1},"8":{"i":1}},"yi":{"0":{"i":9260},"1":{"i":9575},"2":{"i":950},"3":{"i":17}},"cv":{"0":{"i":10112},"1":{"i":12990},"2":{"i":3290},"3":{"i":439},"4":{"i":85},"5":{"i":12},"6":{"i":1}},"ar":{"0":{"i":5490},"1":{"i":46044},"2":{"i":15054},"3":{"i":372}},"pa":{"0":{"i":109},"1":{"i":75},"2":{"i":5}},"cy":{"0":{"i":1167},"1":{"i":868},"2":{"i":20}},"hy":{"0":{"i":123997},"1":{"i":91309},"2":{"i":20857},"3":{"i":2579},"4":{"i":280},"5":{"i":50},"6":{"i":8},"7":{"i":2},"9":{"i":2}},"uz":{"0":{"i":780},"1":{"i":14638},"2":{"i":162}},"ky":{"0":{"i":63},"1":{"i":237},"2":{"i":1218},"3":{"i":2255},"4":{"i":3456},"5":{"i":5736},"6":{"i":6435},"7":{"i":3576},"8":{"i":1265},"9":{"i":509},"10":{"i":145},"11":{"i":53},"12":{"i":12},"13":{"i":3},"14":{"i":1}},"an":{"0":{"i":66266},"1":{"i":59254},"2":{"i":20229},"3":{"i":4224},"4":{"i":314},"5":{"i":27},"6":{"i":2}},"ja":{"0":{"i":253440},"1":{"i":89780},"2":{"i":11615},"3":{"i":665},"4":{"i":44},"5":{"i":4}},"ms":{"0":{"i":3788},"1":{"i":17680},"2":{"i":7590},"3":{"i":104730},"4":{"i":31125},"5":{"i":42773},"6":{"i":15274},"7":{"i":7943},"8":{"i":2166},"9":{"i":274},"10":{"i":62},"11":{"i":10},"12":{"i":3},"13":{"i":1}},"br":{"0":{"i":17},"1":{"i":23},"2":{"i":658},"3":{"i":10855},"4":{"i":11903},"5":{"i":11544},"6":{"i":9310},"7":{"i":41},"8":{"i":7},"9":{"i":1},"12":{"i":1}},"su":{"0":{"i":44393},"1":{"i":17909},"2":{"i":2338},"3":{"i":395},"4":{"i":109},"5":{"i":41},"6":{"i":3},"7":{"i":3}},"pt":{"0":{"i":1172174,"c":23165},"1":{"i":860928,"c":43796},"2":{"i":275946,"c":33964},"3":{"i":46500,"c":16104},"4":{"i":7355,"c":2039},"5":{"i":1677,"c":1068},"6":{"i":424,"c":659},"7":{"c":157,"i":81},"8":{"i":23,"c":33},"9":{"c":4,"i":2},"10":{"c":1}},"oc":{"0":{"i":992},"1":{"i":606},"2":{"i":18}},"ht":{"0":{"i":179639},"1":{"i":16794},"2":{"i":8713},"3":{"i":32592},"4":{"i":30564},"5":{"i":13866},"6":{"i":149},"7":{"i":63},"8":{"i":36},"9":{"i":8}},"nn":{"0":{"i":7108},"1":{"i":2396},"2":{"i":26},"3":{"i":2}},"ga":{"0":{"i":13613},"1":{"i":12602},"2":{"i":3685},"3":{"i":396},"4":{"i":93},"5":{"i":27},"6":{"i":3},"7":{"i":3}}}
